asyncfast_cli/__init__.py
asyncfast_cli/__main__.py
asyncfast_cli/cli.py
asyncfast_cli/py.typed
asyncfast_cli-0.32.0.dist-info/licenses/LICENSE
asyncfast_cli-0.32.0.dist-info/WHEEL
asyncfast_cli-0.32.0.dist-info/METADATA
asyncfast_cli-0.32.0.dist-info/RECORD
