Metadata-Version: 2.4
Name: asyncfast-cli
Version: 0.32.0
Summary: Add your description here
Author: jack.burridge
Author-email: jack.burridge <jack.burridge@mail.com>
License-Expression: MIT
License-File: LICENSE
Classifier: Programming Language :: Python :: 3 :: Only
Classifier: Programming Language :: Python :: 3.10
Classifier: Programming Language :: Python :: 3.11
Classifier: Programming Language :: Python :: 3.12
Classifier: Programming Language :: Python :: 3.13
Classifier: Programming Language :: Python :: 3.14
Requires-Dist: amgi-types==0.32.0
Requires-Dist: typer>=0.16.0
Requires-Python: >=3.10
